<?xml version="1.0"?>
<root main_tree_to_execute="BehaviorTree">
    <!-- ////////// -->
    <BehaviorTree ID="BehaviorTree">
        <KeepRunningUntilFailure>
            <ReactiveSequence>
                <Action ID="RequestName" nameID="name_"/>
                <Action ID="Introduction" nameID="name_"/>
            </ReactiveSequence>
        </KeepRunningUntilFailure>
    </BehaviorTree>
    <!-- ////////// -->
    <TreeNodesModel>
        <Action ID="Introduction">
            <input_port name="nameID"/>
        </Action>
        <Action ID="RequestName">
            <output_port name="nameID"/>
        </Action>
    </TreeNodesModel>
    <!-- ////////// -->
</root>
